Metadata-Version: 2.1
Name: testvelikafkaclient
Version: 1.0.4
Summary: veli kafka client <3 (demo)
Author: Konstantine
Author-email: kdvalishvili@veli.store
